ncbi_acc_download/__init__.py
ncbi_acc_download/__main__.py
ncbi_acc_download/core.py
ncbi_acc_download/download.py
ncbi_acc_download/errors.py
ncbi_acc_download/validate.py
ncbi_acc_download/wgs.py
ncbi_acc_download-0.2.9.dist-info/LICENSE
ncbi_acc_download-0.2.9.dist-info/METADATA
ncbi_acc_download-0.2.9.dist-info/WHEEL
ncbi_acc_download-0.2.9.dist-info/entry_points.txt
ncbi_acc_download-0.2.9.dist-info/top_level.txt
ncbi_acc_download-0.2.9.dist-info/RECORD
