Metadata-Version: 2.1
Name: ncbi-acc-download
Version: 0.2.9
Summary: Download genome files from NCBI by accession.
Home-page: https://github.com/kblin/ncbi-acc-download/
Author: Kai Blin
Author-email: kblin@biosustain.dtu.dk
License: Apache Software License
Classifier: Programming Language :: Python
Classifier: Development Status :: 3 - Alpha
Classifier: Intended Audience :: Science/Research
Classifier: Topic :: Scientific/Engineering :: Bio-Informatics
Classifier: License :: OSI Approved :: Apache Software License
Classifier: Operating System :: OS Independent
License-File: LICENSE
Requires-Dist: requests >=2.4.3
Provides-Extra: recursive
Requires-Dist: biopython >=1.79 ; extra == 'recursive'
Provides-Extra: testing
Requires-Dist: pytest ; extra == 'testing'
Requires-Dist: coverage ; extra == 'testing'
Requires-Dist: pytest-cov ; extra == 'testing'
Requires-Dist: requests-mock ; extra == 'testing'
Requires-Dist: pytest-mock ; extra == 'testing'
Requires-Dist: flake8 ; extra == 'testing'
Provides-Extra: validate
Requires-Dist: biopython >=1.79 ; extra == 'validate'
